calculator_gkukse/__init__.py
calculator_gkukse/calculator_gkukse.py
calculator_gkukse-0.0.1.dist-info/WHEEL
calculator_gkukse-0.0.1.dist-info/METADATA
calculator_gkukse-0.0.1.dist-info/RECORD
