Metadata-Version: 2.1
Name: calculator_gkukse
Version: 0.0.1
Summary: A calculator package
Author-email: gkukse <gintare.kuksenaite@gmail.com>
Requires-Python: >=3.7
Classifier: Programming Language :: Python :: 3
Classifier: License :: OSI Approved :: MIT License
Classifier: Operating System :: OS Independent
Project-URL: Homepage, https://github.com/TuringCollegeSubmissions/gkukse-DWWP.1
